tubectrl/__init__.py
tubectrl/tubectrl.py
tubectrl/exceptions/__init__.py
tubectrl/exceptions/authentication.py
tubectrl/exceptions/authorization.py
tubectrl/exceptions/playlist.py
tubectrl/exceptions/video.py
tubectrl/models/__init__.py
tubectrl/models/content_details.py
tubectrl/models/content_rating.py
tubectrl/models/file_details.py
tubectrl/models/livestreaming_details.py
tubectrl/models/localizations.py
tubectrl/models/localized.py
tubectrl/models/page_info.py
tubectrl/models/paid_product_placement_details.py
tubectrl/models/player.py
tubectrl/models/playlist.py
tubectrl/models/playlist_content_details.py
tubectrl/models/playlist_item.py
tubectrl/models/playlist_item_content_details.py
tubectrl/models/playlist_item_response.py
tubectrl/models/playlist_item_snippet.py
tubectrl/models/playlist_item_status.py
tubectrl/models/playlist_list_response.py
tubectrl/models/playlist_player.py
tubectrl/models/playlist_snippet.py
tubectrl/models/playlist_status.py
tubectrl/models/processing_details.py
tubectrl/models/recording_details.py
tubectrl/models/region_restriction.py
tubectrl/models/resource.py
tubectrl/models/resource_id.py
tubectrl/models/response.py
tubectrl/models/snippet.py
tubectrl/models/statistics.py
tubectrl/models/status.py
tubectrl/models/suggestions.py
tubectrl/models/thumbnail.py
tubectrl/models/topic_details.py
tubectrl/models/video.py
tubectrl/models/video_content_details.py
tubectrl/models/video_list_response.py
tubectrl/models/video_snippet.py
tubectrl/models/video_status.py
tubectrl/resources/__init__.py
tubectrl/resources/parsers.py
tubectrl/resources/utils.py
tubectrl/resources/playlist/__init__.py
tubectrl/resources/playlist/parsers.py
tubectrl/resources/playlist/playlist.py
tubectrl/resources/playlist/playlist_iterator.py
tubectrl/resources/playlist_item/__init__.py
tubectrl/resources/playlist_item/parsers.py
tubectrl/resources/playlist_item/playlist_item.py
tubectrl/resources/playlist_item/playlist_items_iterator.py
tubectrl-0.4.0.dist-info/LICENSE
tubectrl-0.4.0.dist-info/METADATA
tubectrl-0.4.0.dist-info/WHEEL
tubectrl-0.4.0.dist-info/top_level.txt
tubectrl-0.4.0.dist-info/RECORD
